pymods/__init__.py
pymods/constants.py
pymods/exceptions.py
pymods/reader.py
pymods/record.py
pymods/writer.py
pymods/tests/__init__.py
pymods/tests/tests.py
pymods-2.0.12.dist-info/LICENSE
pymods-2.0.12.dist-info/METADATA
pymods-2.0.12.dist-info/WHEEL
pymods-2.0.12.dist-info/top_level.txt
pymods-2.0.12.dist-info/RECORD
