Metadata-Version: 2.1
Name: pymods
Version: 2.0.12
Summary: Utility class wrapping lxml for reading data from MODS v3.4 XML metadata into Python data types.
Home-page: https://github.com/mrmiguez/pymods
Author: Matthew Miguez
Author-email: r.m.miguez@gmail.com
License: MIT
Download-URL: https://github.com/mrmiguez/pymods/archive/2.0.12.tar.gz
Keywords: MODS metadata xml
Platform: UNKNOWN
Classifier: Development Status :: 4 - Beta
Classifier: Intended Audience :: Other Audience
Classifier: License :: OSI Approved :: MIT License
Classifier: Natural Language :: English
Classifier: Programming Language :: Python :: 3.3
Classifier: Programming Language :: Python :: 3.4
Classifier: Programming Language :: Python :: 3.5
Classifier: Programming Language :: Python :: 3.6
Classifier: Topic :: Text Processing :: Markup :: XML
License-File: LICENSE
Requires-Dist: lxml (>=2.3)
